HISTORY.rst
README.rst
setup.py
collective/__init__.py
collective.recipe.cmmi.egg-info/PKG-INFO
collective.recipe.cmmi.egg-info/SOURCES.txt
collective.recipe.cmmi.egg-info/dependency_links.txt
collective.recipe.cmmi.egg-info/entry_points.txt
collective.recipe.cmmi.egg-info/namespace_packages.txt
collective.recipe.cmmi.egg-info/not-zip-safe
collective.recipe.cmmi.egg-info/requires.txt
collective.recipe.cmmi.egg-info/top_level.txt
collective/recipe/__init__.py
collective/recipe/cmmi/__init__.py