Metadata-Version: 1.0
Name: collective.recipe.cmmi
Version: 0.5
Summary: Adds small features to zc.recipe.cmmi
Home-page: http://github.com/collective/collective.recipe.cmmi
Author: Florian Schulze
Author-email: florian.schulze@gmx.net
License: ZPL 2.1
Platform: UNKNOWN
